[
  { "id": 1, "name": "Wireless Bluetooth Headphones", "price": 79.99, "description": "Premium sound with noise cancellation.", "imageUrl": "/images/headphones.jpg", "category": "Electronics", "tags": ["audio", "wireless", "headphones"] },
  { "id": 2, "name": "Smart Phone Case", "price": 24.99, "description": "Protective & stylish case for modern smartphones.", "imageUrl": "/images/phone-case.jpg", "category": "Accessories", "tags": ["phone", "case", "protection"] },
  { "id": 3, "name": "Laptop Stand", "price": 45.00, "description": "Ergonomic aluminum design for better posture.", "imageUrl": "/images/laptop-stand.jpg", "category": "Office", "tags": ["laptop", "ergonomic", "desk"] },
  { "id": 4, "name": "USB-C Hub", "price": 39.99, "description": "7-in-1 multi-port adapter for all your devices.", "imageUrl": "/images/usb-hub.jpg", "category": "Electronics", "tags": ["usb", "hub", "adapter"] },
  { "id": 5, "name": "Wireless Charging Pad", "price": 29.99, "description": "Fast charge pad compatible with most phones.", "imageUrl": "/images/charging-pad.jpg", "category": "Electronics", "tags": ["charging", "wireless", "pad"] },
  { "id": 6, "name": "LED String Lights", "price": 19.99, "description": "Outdoor waterproof decorative lighting.", "imageUrl": "/images/string-lights.jpg", "category": "Home", "tags": ["lighting", "outdoor", "decor"] },
  { "id": 7, "name": "Ceramic Plant Pot Set", "price": 34.99, "description": "Modern design set of 3 plant pots.", "imageUrl": "/images/plant-pots.jpg", "category": "Home", "tags": ["plants", "decor", "ceramic"] },
  { "id": 8, "name": "Bamboo Cutting Board", "price": 28.50, "description": "Large durable kitchen essential.", "imageUrl": "/images/cutting-board.jpg", "category": "Kitchen", "tags": ["cooking", "kitchen", "board"] },
  { "id": 9, "name": "Essential Oil Diffuser", "price": 42.99, "description": "Ultrasonic aromatherapy diffuser with lights.", "imageUrl": "/images/diffuser.jpg", "category": "Wellness", "tags": ["aromatherapy", "wellness", "diffuser"] },
  { "id": 10, "name": "Memory Foam Pillow", "price": 35.99, "description": "Hypoallergenic pillow for restful sleep.", "imageUrl": "/images/pillow.jpg", "category": "Bedroom", "tags": ["sleep", "comfort", "pillow"] },
  { "id": 11, "name": "Fitness Tracker Watch", "price": 59.99, "description": "Track steps, heart rate, and sleep cycles.", "imageUrl": "/images/fitness-tracker.jpg", "category": "Fitness", "tags": ["fitness", "wearable", "watch"] },
  { "id": 12, "name": "Portable Bluetooth Speaker", "price": 49.99, "description": "Water-resistant speaker with deep bass.", "imageUrl": "/images/speaker.jpg", "category": "Electronics", "tags": ["audio", "wireless", "speaker"] },
  { "id": 13, "name": "Desk Organizer Set", "price": 21.99, "description": "Keep your workspace neat and tidy.", "imageUrl": "/images/desk-organizer.jpg", "category": "Office", "tags": ["desk", "organization", "office"] },
  { "id": 14, "name": "Reusable Water Bottle", "price": 17.50, "description": "Eco-friendly stainless steel bottle.", "imageUrl": "/images/water-bottle.jpg", "category": "Lifestyle", "tags": ["eco", "hydration", "reusable"] },
  { "id": 15, "name": "Wireless Mouse", "price": 29.50, "description": "Ergonomic design with silent clicks.", "imageUrl": "/images/mouse.jpg", "category": "Electronics", "tags": ["computer", "wireless", "mouse"] },
  { "id": 16, "name": "Yoga Mat", "price": 32.00, "description": "Non-slip surface for all yoga practices.", "imageUrl": "/images/yoga-mat.jpg", "category": "Fitness", "tags": ["yoga", "exercise", "mat"] },
  { "id": 17, "name": "Coffee Grinder", "price": 44.99, "description": "Electric grinder for fresh coffee grounds.", "imageUrl": "/images/coffee-grinder.jpg", "category": "Kitchen", "tags": ["coffee", "kitchen", "appliance"] },
  { "id": 18, "name": "Desk Lamp with USB Port", "price": 38.00, "description": "Adjustable LED lamp with charging port.", "imageUrl": "/images/desk-lamp.jpg", "category": "Office", "tags": ["lighting", "desk", "lamp"] },
  { "id": 19, "name": "Travel Backpack", "price": 65.00, "description": "Lightweight backpack with multiple compartments.", "imageUrl": "/images/backpack.jpg", "category": "Travel", "tags": ["bag", "backpack", "travel"] },
  { "id": 20, "name": "Kitchen Knife Set", "price": 79.00, "description": "Professional stainless steel knife set.", "imageUrl": "/images/knife-set.jpg", "category": "Kitchen", "tags": ["cooking", "knives", "kitchen"] }
]
